pylon/__init__.py
pylon/api.py
pylon/pylon.py
pylon/tray.py
pylon/utils.py
pylon_desktop-0.2.2.dist-info/LICENSE
pylon_desktop-0.2.2.dist-info/METADATA
pylon_desktop-0.2.2.dist-info/WHEEL
pylon_desktop-0.2.2.dist-info/RECORD
